utlvce/__init__.py
utlvce/generators.py
utlvce/main.py
utlvce/model.py
utlvce/score.py
utlvce/utils.py
utlvce-0.1.1.dist-info/LICENSE.txt
utlvce-0.1.1.dist-info/METADATA
utlvce-0.1.1.dist-info/WHEEL
utlvce-0.1.1.dist-info/top_level.txt
utlvce-0.1.1.dist-info/RECORD
