Metadata-Version: 2.1
Name: utlvce
Version: 0.1.1
Summary: UNKNOWN
Home-page: https://github.com/juangamella/ut-lvce
Author: Juan L Gamella
Author-email: juangamella@gmail.com
License: BSD 3-Clause License
Platform: UNKNOWN
License-File: LICENSE.txt
Requires-Dist: numpy (>=1.17.0)
Requires-Dist: cvxpy (>=1.1.15)
Requires-Dist: ges (>=1.0.6)
